teste_fiap/__init__.py
teste_fiap/core.py
teste_fiap_package-1.0.0.dist-info/METADATA
teste_fiap_package-1.0.0.dist-info/WHEEL
teste_fiap_package-1.0.0.dist-info/top_level.txt
teste_fiap_package-1.0.0.dist-info/RECORD
