Metadata-Version: 2.4
Name: teste_fiap-package
Version: 1.0.0
Summary: Descricao da sua lib teste_fiap
Home-page: https://github.com/milerazevedo0/teste_fiap
Author: Miler Azevedo
Author-email: estudos.miler@gmail.com
License: MIT
Dynamic: author
Dynamic: author-email
Dynamic: description
Dynamic: description-content-type
Dynamic: home-page
Dynamic: license
Dynamic: summary
